ssm/__init__.py
ssm/__main__.py
ssm/__version__.py
ssm/ssm.py
ssm_svg-0.1.0.dist-info/LICENSE
ssm_svg-0.1.0.dist-info/METADATA
ssm_svg-0.1.0.dist-info/WHEEL
ssm_svg-0.1.0.dist-info/entry_points.txt
ssm_svg-0.1.0.dist-info/top_level.txt
ssm_svg-0.1.0.dist-info/RECORD
