Metadata-Version: 2.1
Name: ssm-svg
Version: 0.1.0
Summary: SVG spritesheet maker
Home-page: https://github.com/obeezzy/ssm
Author: Chronic Coder
Author-email: efeoghene.obebeduo@gmail.com
License: MIT
Classifier: License :: OSI Approved :: MIT License
Classifier: Programming Language :: Python :: 3
Classifier: Programming Language :: Python :: 3.9
License-File: LICENSE
Requires-Dist: lxml
